LeafletSC/__init__.py
LeafletSC/beta_binomial_mix/__init__.py
LeafletSC/beta_binomial_mix/calculate_cellstate_consistency.py
LeafletSC/beta_binomial_mix/modeling.py
LeafletSC/clustering/__init__.py
LeafletSC/clustering/find_intron_clusters.py
LeafletSC/clustering/load_cluster_data.py
LeafletSC/clustering/prepare_model_input.py
LeafletSC/simulation/__init__.py
LeafletSC/simulation/simulate_counts.py
LeafletSC/utils/__init__.py
LeafletSC/utils/helpers.py
LeafletSC/utils/splicing_utils.py
LeafletSC/utils/visualization.py
tests/__init__.py
LeafletSC-0.2.16.dist-info/LICENSE
LeafletSC-0.2.16.dist-info/METADATA
LeafletSC-0.2.16.dist-info/WHEEL
LeafletSC-0.2.16.dist-info/top_level.txt
LeafletSC-0.2.16.dist-info/RECORD
