Metadata-Version: 2.1
Name: LeafletSC
Version: 0.2.16
Summary: Alternative splicing quantification in single cells with Leaflet
Home-page: https://github.com/daklab/Leaflet
Author: Karin Isaev, Columbia University and NYGC
Author-email: ki2255@cumc.columbia.edu
License: MIT
Classifier: Programming Language :: Python :: 3
Classifier: License :: OSI Approved :: MIT License
Classifier: Operating System :: OS Independent
Requires-Python: >=3.10
License-File: LICENSE
Requires-Dist: gtfparse ==2.5.0
Requires-Dist: matplotlib
Requires-Dist: numpy
Requires-Dist: pandas
Requires-Dist: pyranges ==0.0.129
Requires-Dist: scanpy
Requires-Dist: scikit-learn
Requires-Dist: scipy
Requires-Dist: seaborn
Requires-Dist: setuptools
Requires-Dist: torch
Requires-Dist: tqdm
Requires-Dist: umap
Requires-Dist: tables
Requires-Dist: polars-lts-cpu
